{
    "key": "group_6209fb63b61de",
    "title": "Main menu",
    "fields": [
        {
            "key": "field_6209fb7e27eda",
            "label": "Main tabs",
            "name": "",
            "type": "accordion",
            "instructions": "",
            "required": 0,
            "conditional_logic": 0,
            "wrapper": {
                "width": "",
                "class": "",
                "id": ""
            },
            "open": 0,
            "multi_expand": 0,
            "endpoint": 0
        },
        {
            "key": "field_620a18986ab14",
            "label": "General",
            "name": "",
            "type": "tab",
            "instructions": "",
            "required": 0,
            "conditional_logic": 0,
            "wrapper": {
                "width": "",
                "class": "",
                "id": ""
            },
            "placement": "top",
            "endpoint": 0
        },
        {
            "key": "field_620a2cd9b64bb",
            "label": "Gap",
            "name": "gap",
            "type": "range",
            "instructions": "",
            "required": 0,
            "conditional_logic": 0,
            "wrapper": {
                "width": "",
                "class": "",
                "id": ""
            },
            "default_value": "",
            "min": "",
            "max": 50,
            "step": 1,
            "prepend": "",
            "append": ""
        },
        {
            "key": "field_620a2440d0aec",
            "label": "Padding X",
            "name": "padding",
            "type": "range",
            "instructions": "",
            "required": 0,
            "conditional_logic": 0,
            "wrapper": {
                "width": "",
                "class": "",
                "id": ""
            },
            "default_value": "",
            "min": "",
            "max": 25,
            "step": "",
            "prepend": "",
            "append": ""
        },
        {
            "key": "field_620a2b27605b3",
            "label": "Padding Y",
            "name": "padding_y",
            "type": "range",
            "instructions": "",
            "required": 0,
            "conditional_logic": 0,
            "wrapper": {
                "width": "",
                "class": "",
                "id": ""
            },
            "default_value": "",
            "min": "",
            "max": 25,
            "step": "",
            "prepend": "",
            "append": ""
        },
        {
            "key": "field_620a182f27edb",
            "label": "Background",
            "name": "background",
            "type": "color_picker",
            "instructions": "",
            "required": 0,
            "conditional_logic": 0,
            "wrapper": {
                "width": "",
                "class": "",
                "id": ""
            },
            "default_value": "",
            "enable_opacity": 1,
            "return_format": "string"
        },
        {
            "key": "field_620a185d27edc",
            "label": "Text color",
            "name": "text_color",
            "type": "color_picker",
            "instructions": "",
            "required": 0,
            "conditional_logic": 0,
            "wrapper": {
                "width": "",
                "class": "",
                "id": ""
            },
            "default_value": "",
            "enable_opacity": 0,
            "return_format": "string"
        },
        {
            "key": "field_620a18aa6ab15",
            "label": "Hover",
            "name": "",
            "type": "tab",
            "instructions": "",
            "required": 0,
            "conditional_logic": 0,
            "wrapper": {
                "width": "",
                "class": "",
                "id": ""
            },
            "placement": "top",
            "endpoint": 0
        },
        {
            "key": "field_620a18e65590e",
            "label": "Background",
            "name": "hover_background",
            "type": "color_picker",
            "instructions": "",
            "required": 0,
            "conditional_logic": 0,
            "wrapper": {
                "width": "",
                "class": "",
                "id": ""
            },
            "default_value": "",
            "enable_opacity": 1,
            "return_format": "string"
        },
        {
            "key": "field_620a18f15590f",
            "label": "Text color",
            "name": "hover_text_color",
            "type": "color_picker",
            "instructions": "",
            "required": 0,
            "conditional_logic": 0,
            "wrapper": {
                "width": "",
                "class": "",
                "id": ""
            },
            "default_value": "",
            "enable_opacity": 0,
            "return_format": "string"
        },
        {
            "key": "field_620a2e631f237",
            "label": "Sub menu",
            "name": "",
            "type": "accordion",
            "instructions": "",
            "required": 0,
            "conditional_logic": 0,
            "wrapper": {
                "width": "",
                "class": "",
                "id": ""
            },
            "open": 0,
            "multi_expand": 0,
            "endpoint": 0
        },
        {
            "key": "field_620a2e851f238",
            "label": "General",
            "name": "",
            "type": "tab",
            "instructions": "",
            "required": 0,
            "conditional_logic": 0,
            "wrapper": {
                "width": "",
                "class": "",
                "id": ""
            },
            "placement": "top",
            "endpoint": 0
        },
        {
            "key": "field_620a2faaf6714",
            "label": "width",
            "name": "width",
            "type": "number",
            "instructions": "",
            "required": 0,
            "conditional_logic": 0,
            "wrapper": {
                "width": "",
                "class": "",
                "id": ""
            },
            "default_value": 200,
            "placeholder": "",
            "prepend": "",
            "append": "",
            "min": "",
            "max": "",
            "step": ""
        },
        {
            "key": "field_620b38c454762",
            "label": "Two columns",
            "name": "two_columns",
            "type": "true_false",
            "instructions": "",
            "required": 0,
            "conditional_logic": 0,
            "wrapper": {
                "width": "",
                "class": "",
                "id": ""
            },
            "message": "",
            "default_value": 0,
            "ui": 1,
            "ui_on_text": "",
            "ui_off_text": ""
        },
        {
            "key": "field_620b479b8e39d",
            "label": "Sub menu class",
            "name": "sub_menu_class",
            "type": "text",
            "instructions": "",
            "required": 0,
            "conditional_logic": [
                [
                    {
                        "field": "field_620b38c454762",
                        "operator": "==",
                        "value": "1"
                    }
                ]
            ],
            "wrapper": {
                "width": "",
                "class": "",
                "id": ""
            },
            "default_value": "",
            "placeholder": "",
            "prepend": "",
            "append": "",
            "maxlength": ""
        },
        {
            "key": "field_620b2f59d5d74",
            "label": "background",
            "name": "sub_menu_background",
            "type": "color_picker",
            "instructions": "",
            "required": 0,
            "conditional_logic": 0,
            "wrapper": {
                "width": "",
                "class": "",
                "id": ""
            },
            "default_value": "",
            "enable_opacity": 1,
            "return_format": "string"
        },
        {
            "key": "field_620b59a61a2f3",
            "label": "Separator",
            "name": "separator",
            "type": "color_picker",
            "instructions": "",
            "required": 0,
            "conditional_logic": 0,
            "wrapper": {
                "width": "",
                "class": "",
                "id": ""
            },
            "default_value": "",
            "enable_opacity": 1,
            "return_format": "string"
        },
        {
            "key": "field_620b3081b83e2",
            "label": "link background",
            "name": "sub_menu_link_background",
            "type": "color_picker",
            "instructions": "",
            "required": 0,
            "conditional_logic": 0,
            "wrapper": {
                "width": "",
                "class": "",
                "id": ""
            },
            "default_value": "",
            "enable_opacity": 1,
            "return_format": "string"
        },
        {
            "key": "field_620b3099b83e3",
            "label": "link text color",
            "name": "sub_menu_link_text_color",
            "type": "color_picker",
            "instructions": "",
            "required": 0,
            "conditional_logic": 0,
            "wrapper": {
                "width": "",
                "class": "",
                "id": ""
            },
            "default_value": "",
            "enable_opacity": 0,
            "return_format": "string"
        },
        {
            "key": "field_620b34a7792cc",
            "label": "Hover",
            "name": "",
            "type": "tab",
            "instructions": "",
            "required": 0,
            "conditional_logic": 0,
            "wrapper": {
                "width": "",
                "class": "",
                "id": ""
            },
            "placement": "top",
            "endpoint": 0
        },
        {
            "key": "field_620b34b8792cd",
            "label": "Link background",
            "name": "sub_menu_link_background_hover",
            "type": "color_picker",
            "instructions": "",
            "required": 0,
            "conditional_logic": 0,
            "wrapper": {
                "width": "",
                "class": "",
                "id": ""
            },
            "default_value": "",
            "enable_opacity": 1,
            "return_format": "string"
        },
        {
            "key": "field_620b34f4792ce",
            "label": "Link text color",
            "name": "submenu_link_text_color_hover",
            "type": "color_picker",
            "instructions": "",
            "required": 0,
            "conditional_logic": 0,
            "wrapper": {
                "width": "",
                "class": "",
                "id": ""
            },
            "default_value": "",
            "enable_opacity": 0,
            "return_format": "string"
        },
        {
            "key": "field_624854bb31bc9",
            "label": "End of tab",
            "name": "",
            "type": "accordion",
            "instructions": "",
            "required": 0,
            "conditional_logic": 0,
            "wrapper": {
                "width": "",
                "class": "",
                "id": ""
            },
            "open": 0,
            "multi_expand": 0,
            "endpoint": 1
        }
    ],
    "location": [
        [
            {
                "param": "block",
                "operator": "==",
                "value": "acf\/main-menu"
            }
        ]
    ],
    "menu_order": 0,
    "position": "normal",
    "style": "default",
    "label_placement": "top",
    "instruction_placement": "label",
    "hide_on_screen": "",
    "active": true,
    "description": "",
    "show_in_rest": 0,
    "modified": 1648907945
}